ap/__init__.py
ap/lab.py
akagami-0.0.1.dist-info/METADATA
akagami-0.0.1.dist-info/WHEEL
akagami-0.0.1.dist-info/top_level.txt
akagami-0.0.1.dist-info/RECORD
