Metadata-Version: 2.1
Name: akagami
Version: 0.0.1
Summary: Lab programs
Home-page: UNKNOWN
Author: akagami2410 (Akagami)
Author-email: <audaciousghost2@gmail.com>
License: UNKNOWN
Keywords: python,video,stream,video stream,camera stream,sockets
Platform: UNKNOWN
Classifier: Operating System :: Unix
Classifier: Operating System :: MacOS :: MacOS X
Classifier: Operating System :: Microsoft :: Windows
